Metadata-Version: 2.4
Name: liger_kernel
Version: 0.6.1
Summary: Efficient Triton kernels for LLM Training
License: BSD 2-CLAUSE LICENSE
Project-URL: Homepage, https://github.com/linkedin/Liger-Kernel
License-File: LICENSE
License-File: NOTICE
Requires-Dist: torch>=2.1.2
Requires-Dist: triton>=2.3.1
Provides-Extra: dev
Requires-Dist: transformers>=4.49.0; extra == "dev"
Requires-Dist: matplotlib>=3.7.2; extra == "dev"
Requires-Dist: flake8>=4.0.1.1; extra == "dev"
Requires-Dist: black>=24.4.2; extra == "dev"
Requires-Dist: isort>=5.13.2; extra == "dev"
Requires-Dist: pytest>=7.1.2; extra == "dev"
Requires-Dist: pytest-xdist; extra == "dev"
Requires-Dist: pytest-rerunfailures; extra == "dev"
Requires-Dist: datasets>=2.19.2; extra == "dev"
Requires-Dist: seaborn; extra == "dev"
Requires-Dist: mkdocs; extra == "dev"
Requires-Dist: mkdocs-material; extra == "dev"
Requires-Dist: torchvision>=0.20; extra == "dev"
Dynamic: license-file
Dynamic: provides-extra
Dynamic: requires-dist
